comchem/__init__.py
pycomchem-0.3.dist-info/LICENSE.txt
pycomchem-0.3.dist-info/WHEEL
pycomchem-0.3.dist-info/METADATA
pycomchem-0.3.dist-info/RECORD
