Metadata-Version: 2.1
Name: pycomchem
Version: 0.3
Summary: Python library for accessing the CommonChemistry.org API
Home-page: https://github.com/stuchalk/pyComChem
License: MIT
Keywords: common chemistry,api,cas,registry number
Author: Stuart Chalk
Author-email: schalk@unf.edu
Requires-Python: >=3.7,<4.0
Classifier: License :: OSI Approved :: MIT License
Classifier: Operating System :: OS Independent
Classifier: Programming Language :: Python :: 3
Classifier: Programming Language :: Python :: 3.7
Classifier: Programming Language :: Python :: 3.8
Classifier: Programming Language :: Python :: 3.9
Classifier: Programming Language :: Python :: 3.10
Classifier: Programming Language :: Python :: 3.11
Classifier: Programming Language :: Python :: 3
Requires-Dist: cairosvg (>=2.5.2,<3.0.0)
Project-URL: Repository, https://github.com/stuchalk/pyComChem
